{
  "lastUpdate": "02/01/2026, 08:03:00 PM",
  "lastUpdateISO": "2026-02-02T04:03:00.159Z",
  "proxyBaseUrl": "http://192.168.1.173:3000",
  "localIP": "192.168.1.173",
  "streamCount": 5,
  "streams": [
    {
      "id": "nba-2026-02-01-cle-por",
      "title": "Cleveland Cavaliers vs. Portland Trail Blazers",
      "channel": "",
      "href": "https://ppv.to/live/nba/2026-02-01/cle-por",
      "thumbnail": "https://api.ppv.to/assets/thumb/a6af5ced48b0b968c8b2c6e5410e1ed4-thumbnail.jpg",
      "proxyPaths": [
        "/proxy/game/nba-2026-02-01-cle-por"
      ]
    },
    {
      "id": "nba-2026-02-01-okc-den",
      "title": "Oklahoma City Thunder vs. Denver Nuggets",
      "channel": "",
      "href": "https://ppv.to/live/nba/2026-02-01/okc-den",
      "thumbnail": "https://api.ppv.to/assets/thumb/df7c88c88ef489be45812da0fb14d42c-thumbnail.jpg",
      "proxyPaths": [
        "/proxy/game/nba-2026-02-01-okc-den"
      ]
    },
    {
      "id": "zuffa-boxing-02",
      "title": "Zuffa Boxing 02",
      "channel": "",
      "href": "https://ppv.to/live/zuffa-boxing-02",
      "thumbnail": "https://api.ppv.to/assets/thumb/2648490806f1849768a886b4cf21df80-thumbnail.jpg",
      "proxyPaths": [
        "/proxy/game/zuffa-boxing-02"
      ]
    },
    {
      "id": "nhl-2026-02-01-vgk-ana",
      "title": "Vegas Golden Knights vs. Anaheim Ducks",
      "channel": "",
      "href": "https://ppv.to/live/nhl/2026-02-01/vgk-ana",
      "thumbnail": "https://api.ppv.to/assets/thumb/1270a7e9ee5190c56d9a23cf5fa30ffb-thumbnail.jpg",
      "proxyPaths": [
        "/proxy/game/nhl-2026-02-01-vgk-ana"
      ]
    },
    {
      "id": "the-68th-annual-grammy-awards",
      "title": "The 68th Annual Grammy Awards",
      "channel": "",
      "href": "https://ppv.to/live/the-68th-annual-grammy-awards",
      "thumbnail": "https://api.ppv.to/assets/thumb/93e0158d9a8e47c06888a286c32a6916-thumbnail.jpg",
      "proxyPaths": [
        "/proxy/game/the-68th-annual-grammy-awards"
      ]
    }
  ]
}